quantalogic_toolbox_files/__init__.py
quantalogic_toolbox_files/tools.py
quantalogic_toolbox_files-0.4.1.dist-info/METADATA
quantalogic_toolbox_files-0.4.1.dist-info/WHEEL
quantalogic_toolbox_files-0.4.1.dist-info/entry_points.txt
quantalogic_toolbox_files-0.4.1.dist-info/RECORD
